nestipy_schedule/__init__.py
nestipy_schedule/schedule_builder.py
nestipy_schedule/schedule_decorator.py
nestipy_schedule/schedule_metadata.py
nestipy_schedule/schedule_module.py
nestipy_schedule/schedule_registry.py
nestipy_schedule-0.1.3.dist-info/LICENSE
nestipy_schedule-0.1.3.dist-info/METADATA
nestipy_schedule-0.1.3.dist-info/WHEEL
nestipy_schedule-0.1.3.dist-info/RECORD
