Metadata-Version: 2.1
Name: nestipy-schedule
Version: 0.1.3
Summary: 
Author: tsiresymila
Author-email: tsiresymila@gmail.com
Requires-Python: >=3.11,<4.0
Classifier: Programming Language :: Python :: 3
Classifier: Programming Language :: Python :: 3.11
Classifier: Programming Language :: Python :: 3.12
Requires-Dist: apscheduler (>=3.10.4,<4.0.0)
